k2hdkc/__init__.py
k2hdkc/k2hdkc.py
k2hdkc-1.0.1.dist-info/LICENSE
k2hdkc-1.0.1.dist-info/METADATA
k2hdkc-1.0.1.dist-info/WHEEL
k2hdkc-1.0.1.dist-info/top_level.txt
k2hdkc-1.0.1.dist-info/RECORD
