Metadata-Version: 2.1
Name: k2hdkc
Version: 1.0.1
Summary: A module for k2hdkc from antpickax
Home-page: https://github.com/yahoojapan/k2hdkc_python
Author: Hirotaka Wakabayashi
Author-email: hiwakaba@yahoo-corp.jp
Project-URL: Bug Tracker, https://github.com/yahoojapan/k2hdkc_python/issues
Classifier: Programming Language :: Python :: 3
Classifier: License :: OSI Approved :: MIT License
Classifier: Operating System :: POSIX :: Linux
Requires-Python: >=3.6
License-File: LICENSE
